{
  "Parameters" : {
    "SandboxSafeStorageBaseUrl": "https://14ej9p2krd.execute-api.eu-south-1.amazonaws.com/dev",
    "NotificationCheckAddress": "true",
    "IsLollipopActive": "false",
    "MaxAttachmentsCount": "15",
    "MaxRecipientsCount": "15",
    "LollipopExpectedLcOriginalUrl": "https://localhost:8080/delivery/notifications/received/*",
    "LollipopEnableConsumerLogging": "true",
    "LollipopAssertionRestUri": "http://localhost:3000",
    "LollipopIdpClientBaseUri": "http://localhost:3001"
  }
}
